LICENSE
README.md
setup.cfg
setup.py
de_billing_tools/__init__.py
de_billing_tools/nem12.py
de_billing_tools.egg-info/PKG-INFO
de_billing_tools.egg-info/SOURCES.txt
de_billing_tools.egg-info/dependency_links.txt
de_billing_tools.egg-info/requires.txt
de_billing_tools.egg-info/top_level.txt